[
  {
    "id": "superbid",
    "name": "Superbid",
    "url": "https://www.superbid.com.br",
    "priority": "Alta",
    "type": "marketplace",
    "notes": "Plataforma dinâmica; muitas páginas carregam via JS — Playwright recomendado; API privada possível por parceria.",
    "fields_to_extract": ["source_lot_id", "title", "description", "image_url", "auction_start_at", "auction_end_at", "location", "price_start", "lot_url", "raw_payload"],
    "selectors_notes": "Página dinâmica; localizar card de lote e link; detalhes em página interna com JSON embutido ou carregado via XHR.",
    "requires": "Playwright",
    "contact_possible": true
  },
  {
    "id": "copart",
    "name": "Copart Brasil",
    "url": "https://www.copart.com.br",
    "priority": "Alta",
    "type": "marketplace",
    "notes": "Alto volume; parte do conteúdo via JS; verificar endpoints XHR internos; parceria útil.",
    "fields_to_extract": ["source_lot_id", "title", "description", "image_url", "auction_start_at", "auction_end_at", "location", "price_start", "lot_url", "raw_payload"],
    "selectors_notes": "Usa API XHR retornando JSON em algumas rotas; pode economizar tempo consumindo essas APIs internas quando possível.",
    "requires": "Playwright / Axios",
    "contact_possible": true
  },
  {
    "id": "sodre",
    "name": "Sodré Santoro",
    "url": "https://www.sodresantoro.com.br",
    "priority": "Alta",
    "type": "house",
    "notes": "Site regional com buscas e listagem; já existe scraper no projeto; Playwright usado anteriormente.",
    "fields_to_extract": ["source_lot_id", "title", "description", "image_url", "auction_start_at", "auction_end_at", "location", "lot_url", "raw_payload"],
    "selectors_notes": "Busca por POST/GET para endpoint interno; detalhes na página do lote; date parsing necessário.",
    "requires": "Playwright",
    "contact_possible": false
  },
  {
    "id": "autotran",
    "name": "AutoTran Leilões",
    "url": "https://autotranleiloes.org",
    "priority": "Alta",
    "type": "house",
    "notes": "Foco em veículos; pode ter páginas estáticas e dinâmicas; já tem scraper histórico.",
    "fields_to_extract": ["source_lot_id", "title", "image_url", "auction_start_at", "auction_end_at", "location", "lot_url", "raw_payload"],
    "selectors_notes": "Verificar listagem por página; pode ser extraído com Cheerio quando estático.",
    "requires": "Axios + Cheerio / Playwright se necessário",
    "contact_possible": false
  },
  {
    "id": "pestana",
    "name": "Pestana Leilões",
    "url": "https://pestanaleiloes.com.br",
    "priority": "Alta",
    "type": "house",
    "notes": "Leiloeiro com sessões por região; páginas geralmente estáticas.",
    "fields_to_extract": ["source_lot_id", "title", "description", "image_url", "auction_start_at", "auction_end_at", "location", "lot_url"],
    "selectors_notes": "Cheerio suficiente na maioria dos casos; validar datas/formato.",
    "requires": "Axios + Cheerio",
    "contact_possible": false
  },
  {
    "id": "marca_leiloes",
    "name": "Marca Leilões",
    "url": "https://marcaleiloes.com.br",
    "priority": "Alta",
    "type": "house",
    "notes": "Presença nacional; verificar endpoints de listagem e detalhes.",
    "fields_to_extract": ["source_lot_id", "title", "image_url", "auction_start_at", "auction_end_at", "location", "lot_url"],
    "selectors_notes": "Normalmente HTML estático com links para detalhes.",
    "requires": "Axios + Cheerio",
    "contact_possible": false
  },
  {
    "id": "leiloes_ms",
    "name": "Leilões MS",
    "url": "https://leiloesonlinems.com.br",
    "priority": "Alta",
    "type": "project_internal",
    "notes": "Fonte já integrada no projeto; manter compatibilidade e reaproveitar código.",
    "fields_to_extract": ["source_lot_id", "title", "description", "image_url", "auction_start_at", "auction_end_at", "lot_url", "raw_payload"],
    "selectors_notes": "Existente no repositório; revisar e padronizar com template.",
    "requires": "Axios + Cheerio",
    "contact_possible": false
  },
  {
    "id": "zukerman",
    "name": "Zukerman Leilões",
    "url": "https://www.zukerman.com.br",
    "priority": "Média",
    "type": "house",
    "notes": "Casa grande com muitas sessões; consultar formato de página e calendário.",
    "fields_to_extract": ["source_lot_id", "title", "image_url", "auction_start_at", "auction_end_at", "location", "lot_url"],
    "selectors_notes": "Verificar se listas paginam via query params; Cheerio/Playwright conforme necessidade.",
    "requires": "Axios + Cheerio / Playwright",
    "contact_possible": false
  },
  {
    "id": "tribunais",
    "name": "Portais Judiciais (TJs)",
    "url": "https://www.tjrs.jus.br/ (exemplo: TJs estaduais)",
    "priority": "Alta",
    "type": "public",
    "notes": "Leilões judiciais contendo veículos apreendidos; importante fonte oficial.",
    "fields_to_extract": ["source_lot_id", "title", "description", "auction_start_at", "auction_end_at", "location", "process_number", "lot_url"],
    "selectors_notes": "Sites diferentes por tribunal; implementar adaptadores por estado.",
    "requires": "Axios + Cheerio",
    "contact_possible": false
  },
  {
    "id": "detran",
    "name": "DETRAN (estaduais)",
    "url": "https://www.detran.sp.gov.br (exemplo)",
    "priority": "Alta",
    "type": "public",
    "notes": "Leilões de veículos apreendidos; variação entre estados exige adaptadores.",
    "fields_to_extract": ["source_lot_id", "title", "description", "auction_start_at", "auction_end_at", "location", "lot_url"],
    "selectors_notes": "Páginas em HTML estático em muitos estados; Cheerio geralmente suficiente.",
    "requires": "Axios + Cheerio",
    "contact_possible": false
  },
  {
    "id": "prefeituras",
    "name": "Prefeituras / Órgãos Municipais",
    "url": "varios portais municipais",
    "priority": "Média",
    "type": "public",
    "notes": "Leilões e vendas públicas de prefeituras; fontes dispersas.",
    "fields_to_extract": ["source_lot_id", "title", "description", "auction_start_at", "auction_end_at", "location", "lot_url"],
    "selectors_notes": "Muitos padrões; usar crawler de descoberta para localizar páginas relevantes.",
    "requires": "Axios + Cheerio",
    "contact_possible": false
  },
  {
    "id": "freitas",
    "name": "Freitas Leilões",
    "url": "https://www.freitasleiloes.com.br",
    "priority": "Média",
    "type": "house",
    "notes": "Leiloeiro regional com lotes veiculares.",
    "fields_to_extract": ["source_lot_id", "title", "image_url", "auction_start_at", "auction_end_at", "lot_url"],
    "selectors_notes": "Geralmente estático; Cheerio recomendado.",
    "requires": "Axios + Cheerio",
    "contact_possible": false
  },
  {
    "id": "megaleiloes",
    "name": "Megaleilões",
    "url": "https://www.megaleiloes.com.br",
    "priority": "Média",
    "type": "platform",
    "notes": "Plataforma de leilões com várias categorias.",
    "fields_to_extract": ["source_lot_id", "title", "description", "auction_start_at", "auction_end_at", "lot_url"],
    "selectors_notes": "Verificar se existe API pública; caso contrário, usar parsing das listagens.",
    "requires": "Axios + Cheerio / Playwright",
    "contact_possible": false
  },
  {
    "id": "leilaovip",
    "name": "LeilãoVIP / LanceVIP",
    "url": "https://www.leilaovip.com.br",
    "priority": "Média",
    "type": "platform",
    "notes": "Players regionais/online com lotes de sucata.",
    "fields_to_extract": ["source_lot_id", "title", "auction_start_at", "auction_end_at", "lot_url"],
    "selectors_notes": "Normalmente estático; verificar detalhes do lote.",
    "requires": "Axios + Cheerio",
    "contact_possible": false
  },
  {
    "id": "agregadores",
    "name": "Agregadores / LeiloesBrasil",
    "url": "https://www.leiloesbrasil.com.br (exemplo)",
    "priority": "Média",
    "type": "aggregator",
    "notes": "Agregadores podem fornecer ponte para múltiplas fontes, útil para descoberta rápida.",
    "fields_to_extract": ["title", "source_hint", "lot_url"],
    "selectors_notes": "Usar como input para descoberta; nem sempre fonte primária.",
    "requires": "Axios + Cheerio",
    "contact_possible": false
  }
]
